coloform/__about__.py
coloform/__init__.py
coloform/ansi.py
coloform/color.py
coloform/demo.py
coloform-0.0.1a8.dist-info/METADATA
coloform-0.0.1a8.dist-info/WHEEL
coloform-0.0.1a8.dist-info/RECORD
