Metadata-Version: 2.4
Name: coloform
Version: 0.0.1a8
Dynamic: Author
Dynamic: Author-email
Dynamic: Summary
Dynamic: Maintainer
Dynamic: Maintainer-email
Project-URL: Repository, https://github.com/FynnFreyer/coloform
Project-URL: Issues, https://github.com/FynnFreyer/coloform/issues
Classifier: Development Status :: 1 - Planning
Classifier: Operating System :: POSIX :: Linux
Classifier: Programming Language :: Python :: 3
Requires-Python: >=3.8
Requires-Dist: colorama
Provides-Extra: dev
Requires-Dist: autopep8; extra == 'dev'
Requires-Dist: isort; extra == 'dev'
Requires-Dist: mypy; extra == 'dev'
Requires-Dist: ruff; extra == 'dev'
Requires-Dist: types-colorama; extra == 'dev'
Requires-Dist: uv; extra == 'dev'
